setup.py
pyarkosclient/__init__.py
pyarkosclient/errors.py
pyarkosclient/frameworks.py
pyarkosclient.egg-info/PKG-INFO
pyarkosclient.egg-info/SOURCES.txt
pyarkosclient.egg-info/dependency_links.txt
pyarkosclient.egg-info/requires.txt
pyarkosclient.egg-info/top_level.txt