Metadata-Version: 1.1
Name: pyarkosclient
Version: 0.3
Summary: Python bindings for remote management of arkOS servers via their Kraken REST API
Home-page: https://arkos.io
Author: Jacob Cook
Author-email: jacob@citizenweb.io
License: GPLv3
Platform: UNKNOWN
Classifier: Development Status :: 3 - Alpha
Classifier: License :: OSI Approved :: GNU General Public License v3 or later (GPLv3+)
Classifier: Operating System :: Unix
